daikinitm/__init__.py
daikinitm/daikinitm.py
daikinitm-0.82.dist-info/LICENSE.txt
daikinitm-0.82.dist-info/METADATA
daikinitm-0.82.dist-info/WHEEL
daikinitm-0.82.dist-info/top_level.txt
daikinitm-0.82.dist-info/RECORD
