Metadata-Version: 2.1
Name: daikinitm
Version: 0.82
Summary: Daikin ITM Controller
Home-page: https://github.com/ancutrs/daikinitm
Author: Anucha
Author-email: utrsanc@gmail.com
License: AnuchaU
Keywords: daikin itm
Platform: UNKNOWN
License-File: LICENSE.txt
